srvlookup.py
srvlookup-2.0.0.dist-info/DESCRIPTION.rst
srvlookup-2.0.0.dist-info/METADATA
srvlookup-2.0.0.dist-info/RECORD
srvlookup-2.0.0.dist-info/WHEEL
srvlookup-2.0.0.dist-info/metadata.json
srvlookup-2.0.0.dist-info/top_level.txt
srvlookup-2.0.0.dist-info/zip-safe
